chainmap/__init__.py
chainmap/chainmap.py
chainmap/version.py
chainmap-1.0.2.dist-info/DESCRIPTION.rst
chainmap-1.0.2.dist-info/METADATA
chainmap-1.0.2.dist-info/metadata.json
chainmap-1.0.2.dist-info/RECORD
chainmap-1.0.2.dist-info/top_level.txt
chainmap-1.0.2.dist-info/WHEEL
